{"version":1,"addons":{"formautofill@mozilla.org":{"id":"formautofill@mozilla.org","guid":"{87578ccf-c1f4-4662-8ff9-e05a7ea5a637}","enabled":true,"installed":true,"modified":1748076201278,"type":"extension","scope":4,"foreignInstall":false,"isSyncable":false},"pictureinpicture@mozilla.org":{"id":"pictureinpicture@mozilla.org","guid":"{181f23e5-67c1-4e5e-b17e-6424921fc181}","enabled":true,"installed":true,"modified":1748076201278,"type":"extension","scope":4,"foreignInstall":false,"isSyncable":false},"addons-search-detection@mozilla.com":{"id":"addons-search-detection@mozilla.com","guid":"{3b9a255a-7ac0-4f96-a17c-77786e5a5bd3}","enabled":true,"installed":true,"modified":1748076201278,"type":"extension","scope":4,"foreignInstall":false,"isSyncable":false},"webcompat@mozilla.org":{"id":"webcompat@mozilla.org","guid":"{7bce54b3-e583-48a2-83df-9baa2b8e7cef}","enabled":true,"installed":true,"modified":1748076201278,"type":"extension","scope":4,"foreignInstall":false,"isSyncable":false},"default-theme@mozilla.org":{"id":"default-theme@mozilla.org","guid":"{10306646-e092-4cce-9ac7-4d98d49cc343}","enabled":true,"installed":true,"modified":1748076201279,"type":"theme","scope":4,"foreignInstall":false,"isSyncable":false},"firefox-compact-light@mozilla.org":{"id":"firefox-compact-light@mozilla.org","guid":"{ad17fccc-2b60-4f9a-b0e1-4ae05ba518c3}","enabled":false,"installed":true,"modified":1748076201279,"type":"theme","scope":4,"foreignInstall":false,"isSyncable":false},"firefox-compact-dark@mozilla.org":{"id":"firefox-compact-dark@mozilla.org","guid":"{ac7de6e2-5467-4fb9-92c6-fb72ffacc047}","enabled":false,"installed":true,"modified":1748076201279,"type":"theme","scope":4,"foreignInstall":false,"isSyncable":false},"gmp-gmpopenh264":{"id":"gmp-gmpopenh264","enabled":true,"installed":true,"modified":1748076201279,"type":"plugin","scope":4,"foreignInstall":false},"gmp-widevinecdm":{"id":"gmp-widevinecdm","enabled":true,"installed":true,"modified":1748076201279,"type":"plugin","scope":4,"foreignInstall":false},"sponsorBlocker@ajay.app":{"id":"sponsorBlocker@ajay.app","guid":"{056c4343-2b6d-4ef6-90be-1960e20c73e4}","enabled":true,"installed":true,"modified":1748082672214,"type":"extension","scope":1,"foreignInstall":false,"isSyncable":true},"jid1-MnnxcxisBPnSXQ@jetpack":{"id":"jid1-MnnxcxisBPnSXQ@jetpack","guid":"{d152311c-2cf3-44a1-8378-8dce15bfe1bb}","enabled":true,"installed":true,"modified":1748082772359,"type":"extension","scope":1,"foreignInstall":false,"isSyncable":true},"uBlock0@raymondhill.net":{"id":"uBlock0@raymondhill.net","guid":"{dd4357af-a3a2-4679-8c9b-086c452588f8}","enabled":true,"installed":true,"modified":1748082786010,"type":"extension","scope":1,"foreignInstall":false,"isSyncable":true},"adguardadblocker@adguard.com":{"id":"adguardadblocker@adguard.com","guid":"{ac304b33-e5ec-467c-b45c-8062d6d3e025}","enabled":true,"installed":true,"modified":1748082798951,"type":"extension","scope":1,"foreignInstall":false,"isSyncable":true},"{1ab2bf16-a321-4512-8690-924989617ac4}":{"id":"{1ab2bf16-a321-4512-8690-924989617ac4}","guid":"{2fbf9586-e6ab-45d1-97ae-85e5823f6aa0}","enabled":true,"installed":false,"modified":1756019399372,"type":"extension","scope":1,"foreignInstall":false,"isSyncable":true},"myallychou@gmail.com":{"id":"myallychou@gmail.com","guid":"{298d5167-1a0d-4a4b-bc2d-63062f8018fd}","enabled":true,"installed":true,"modified":1749237595261,"type":"extension","scope":1,"foreignInstall":false,"isSyncable":true},"{7be2ba16-0f1e-4d93-9ebc-5164397477a9}":{"id":"{7be2ba16-0f1e-4d93-9ebc-5164397477a9}","guid":"{89cf9502-af9b-4bcd-8312-c6141f75dd87}","enabled":true,"installed":true,"modified":1756019379550,"type":"extension","scope":1,"foreignInstall":false,"isSyncable":true},"firefox-alpenglow@mozilla.org":{"id":"firefox-alpenglow@mozilla.org","guid":"{3ce36114-caac-4e0c-8476-5b1349602ec2}","enabled":false,"installed":true,"modified":1762082183276,"type":"theme","scope":4,"foreignInstall":false,"isSyncable":false},"data-leak-blocker@mozilla.com":{"id":"data-leak-blocker@mozilla.com","guid":"{9ceeb1a4-38eb-407d-9d79-78fd6b90b793}","enabled":true,"installed":true,"modified":1762082187410,"type":"extension","scope":4,"foreignInstall":false,"isSyncable":false},"ipp-activator@mozilla.com":{"id":"ipp-activator@mozilla.com","guid":"{a5c96d36-1de8-4a2a-b3f6-f8de0d713fe9}","enabled":true,"installed":true,"modified":1762082187411,"type":"extension","scope":4,"foreignInstall":false,"isSyncable":false},"newtab@mozilla.org":{"id":"newtab@mozilla.org","guid":"{585840f8-2ecc-4955-b98c-42c0b1721e2f}","enabled":true,"installed":true,"modified":1762082187411,"type":"extension","scope":4,"foreignInstall":false,"isSyncable":false}},"changes":[[1756019331494,4,"{1ab2bf16-a321-4512-8690-924989617ac4}"],[1756019332379,3,"{1ab2bf16-a321-4512-8690-924989617ac4}"],[1756019379550,1,"{7be2ba16-0f1e-4d93-9ebc-5164397477a9}"],[1756019399372,2,"{1ab2bf16-a321-4512-8690-924989617ac4}"],[1762082183276,1,"firefox-alpenglow@mozilla.org"],[1762082187410,1,"data-leak-blocker@mozilla.com"],[1762082187411,1,"ipp-activator@mozilla.com"],[1762082187411,1,"newtab@mozilla.org"]]}